LICENSE
alex_sudoku/__init__.py
alex_sudoku/config/__init__.py
alex_sudoku/config/constants.py
alex_sudoku/config/paths.py
alex_sudoku/interface/__init__.py
alex_sudoku/interface/command_line.py
alex_sudoku/logs/__init__.py
alex_sudoku/logs/setup_logging.py
alex_sudoku/main.py
alex_sudoku/py.typed
alex_sudoku/VERSION
alex_sudoku-0.2.1.dist-info/entry_points.txt
alex_sudoku-0.2.1.dist-info/LICENSE
alex_sudoku-0.2.1.dist-info/METADATA
alex_sudoku-0.2.1.dist-info/WHEEL
alex_sudoku-0.2.1.dist-info/RECORD
